<?xml version="1.0"?><api><parse title="MediaWiki:Disambiguationspage"><links><pl ns="4" exists="" xml:space="preserve">Wikipedia:Särskiljning</pl><pl ns="4" exists="" xml:space="preserve">Wikipedia:Robotar</pl><pl ns="10" exists="" xml:space="preserve">Mall:Förgrening</pl><pl ns="10" exists="" xml:space="preserve">Mall:Betydelselista</pl><pl ns="10" exists="" xml:space="preserve">Mall:Dab</pl><pl ns="10" exists="" xml:space="preserve">Mall:Disambig</pl><pl ns="10" exists="" xml:space="preserve">Mall:Disambiguation</pl><pl ns="10" exists="" xml:space="preserve">Mall:Flertydig</pl><pl ns="10" exists="" xml:space="preserve">Mall:Förgreningssida</pl><pl ns="10" exists="" xml:space="preserve">Mall:Gaffel</pl><pl ns="10" exists="" xml:space="preserve">Mall:Gren</pl><pl ns="10" exists="" xml:space="preserve">Mall:Grensida</pl><pl ns="10" exists="" xml:space="preserve">Mall:Ortnamn</pl><pl ns="10" exists="" xml:space="preserve">Mall:Trebokstavsförgrening</pl><pl ns="10" exists="" xml:space="preserve">Mall:3Bgren</pl><pl ns="10" exists="" xml:space="preserve">Mall:3LA</pl><pl ns="10" exists="" xml:space="preserve">Mall:3LC</pl><pl ns="10" exists="" xml:space="preserve">Mall:TLAdisambig</pl><pl ns="10" exists="" xml:space="preserve">Mall:Trebokstavsförkortning</pl><pl ns="10" exists="" xml:space="preserve">Mall:Fyrbokstavsförgrening</pl><pl ns="10" exists="" xml:space="preserve">Mall:4LA</pl><pl ns="10" exists="" xml:space="preserve">Mall:4LC</pl><pl ns="10" exists="" xml:space="preserve">Mall:Namnförgrening</pl><pl ns="10" exists="" xml:space="preserve">Mall:Hndis</pl><pl ns="10" exists="" xml:space="preserve">Mall:Namngrensida</pl><pl ns="10" exists="" xml:space="preserve">Mall:Efternamn</pl><pl ns="10" exists="" xml:space="preserve">Mall:Förnamn</pl><pl ns="10" exists="" xml:space="preserve">Mall:Robotskapad förgrening</pl></links></parse></api>